{
  "project_info": {
    "project_number": "829647184082",
    "firebase_url": "https://unityrehabilitationar-default-rtdb.europe-west1.firebasedatabase.app",
    "project_id": "unityrehabilitationar",
    "storage_bucket": "unityrehabilitationar.firebasestorage.app"
  },
  "client": [
    {
      "client_info": {
        "mobilesdk_app_id": "1:829647184082:android:052dde08ad15cf800f8d0b",
        "android_client_info": {
          "package_name": "com.Rafora.RehabilitationAR"
        }
      },
      "oauth_client": [],
      "api_key": [
        {
          "current_key": "AIzaSyCS_0bcdOUjA_5ov_f4eV2nz3bzIJY3fn0"
        }
      ],
      "services": {
        "appinvite_service": {
          "other_platform_oauth_client": []
        }
      }
    }
  ],
  "configuration_version": "1"
}